indic_soundex/__init__.py
indic_soundex/core.py
indic_soundex-0.1.0.dist-info/licenses/LICENSE
indic_soundex-0.1.0.dist-info/METADATA
indic_soundex-0.1.0.dist-info/WHEEL
indic_soundex-0.1.0.dist-info/top_level.txt
indic_soundex-0.1.0.dist-info/RECORD
