Metadata-Version: 2.4
Name: indic-soundex
Version: 0.1.0
Summary: Indic Soundex algorithm for phonetic encoding of Indian names.
Author-email: Mehul Dhikonia <mehul.dhikonia@gmail.com>
License: MIT License
Project-URL: Homepage, https://github.com/maverickMehul/indic-soundex/
Keywords: soundex,phonetics,indic,names,nlp
Classifier: Development Status :: 3 - Alpha
Classifier: Intended Audience :: Developers
Classifier: License :: OSI Approved :: MIT License
Classifier: Programming Language :: Python :: 3
Classifier: Programming Language :: Python :: 3 :: Only
Classifier: Programming Language :: Python :: 3.8
Classifier: Programming Language :: Python :: 3.9
Classifier: Programming Language :: Python :: 3.10
Classifier: Programming Language :: Python :: 3.11
Classifier: Programming Language :: Python :: 3.12
Requires-Python: >=3.8
License-File: LICENSE
Dynamic: license-file
